{
    "success": true,
    "message": "lorem ipsum",
    "content": [
        {
            "id": "1",
            "name": "Chicken",
            "price": "50.00",
            "image_url": "https://www.maangchi.com/wp-content/uploads/2018/02/tongdakgui-finished-650x366.jpg"
        },
        {
            "id": "2",
            "name": "Burger",
            "price": "20.00",
            "image_url": "https://natashaskitchen.com/wp-content/uploads/2019/04/Best-Burger-5-600x900.jpg"
        }
    ]
}
